pyrvtools/__init__.py
pyrvtools/errors.py
pyrvtools/esx_types.py
pyrvtools/pyrvtools.py
pyrvtools-1.0.1.dist-info/DESCRIPTION.rst
pyrvtools-1.0.1.dist-info/METADATA
pyrvtools-1.0.1.dist-info/RECORD
pyrvtools-1.0.1.dist-info/WHEEL
pyrvtools-1.0.1.dist-info/metadata.json
pyrvtools-1.0.1.dist-info/top_level.txt
