Metadata-Version: 2.0
Name: pyrvtools
Version: 1.0.1
Summary: Extract useful information from an RVTools ESX inventory file
Home-page: https://github.com/jbrt/pyrvtools
Author: Julien B.
Author-email: julien@toshokan.fr
License: GPL
Platform: UNKNOWN
Classifier: Development Status :: 5 - Production/Stable
Classifier: Programming Language :: Python :: 3
Classifier: Programming Language :: Python :: 3.1
Classifier: Programming Language :: Python :: 3.2
Classifier: Programming Language :: Python :: 3.3
Classifier: Programming Language :: Python :: 3.4
Classifier: Programming Language :: Python :: 3.5
Classifier: Topic :: Utilities
Classifier: License :: OSI Approved :: GNU General Public License v3 (GPLv3)
Requires-Dist: xlrd
